render_browser/__init__.py
render_browser/render.py
render_browser/templates/index.html
render_browser-0.5.dist-info/LICENSE
render_browser-0.5.dist-info/METADATA
render_browser-0.5.dist-info/WHEEL
render_browser-0.5.dist-info/top_level.txt
render_browser-0.5.dist-info/RECORD
