Metadata-Version: 2.1
Name: render-browser
Version: 0.5
Summary: Render gym environments to a web browser.
Home-page: https://github.com/dhruvramani/gym-render-browser
Author: Dhruv Ramani
Author-email: dhruvramani98@gmail.com
License: UNKNOWN
Platform: UNKNOWN
Classifier: Programming Language :: Python :: 3
Classifier: License :: OSI Approved :: MIT License
Classifier: Operating System :: OS Independent
Requires-Dist: Flask
Requires-Dist: opencv-python
